perfectreports/main_cli.py
perfectreports/temp.py
perfectreports/py/analytics.py
perfectreports/py/commands_api.py
perfectreports/py/custom_reasons.py
perfectreports/py/devices_list.py
perfectreports/py/functions.py
perfectreports/py/html.py
perfectreports/py/temp.py
perfectreports/py/integrations/jira.py
perfectreports/py/integrations/teams.py
perfectreports/py/integrations/google_analytics/g_analytics.py
perfectreports/py/integrations/google_analytics/g_functions.py
perfectreports/py/integrations/google_analytics/g_html.py
perfectreports-0.0.20.dist-info/METADATA
perfectreports-0.0.20.dist-info/WHEEL
perfectreports-0.0.20.dist-info/entry_points.txt
perfectreports-0.0.20.dist-info/top_level.txt
perfectreports-0.0.20.dist-info/RECORD
